wizcraft/__init__.py
wizcraft/categorical.py
wizcraft/data_description.py
wizcraft/download.py
wizcraft/feature_selection.py
wizcraft/imputation.py
wizcraft/io.py
wizcraft/preprocess.py
wiz_craft-1.1.1.dist-info/LICENSE
wiz_craft-1.1.1.dist-info/METADATA
wiz_craft-1.1.1.dist-info/WHEEL
wiz_craft-1.1.1.dist-info/top_level.txt
wiz_craft-1.1.1.dist-info/RECORD
