Metadata-Version: 2.1
Name: wiz-craft
Version: 1.1.1
Summary: A CLI-based dataset preprocessing tool for machine learning tasks. Features include data exploration, null value handling, one-hot encoding, and feature scaling, and download the modified dataset effortlessly.
Home-page: https://github.com/Pinak-Datta/wiz-craft
Author: Pinak Datta
Author-email: pinakdatta2002@gmail.com
License: OSI Approved :: MIT License
Keywords: Dataset preprocessing,Data cleaning,Machine learning,Data manipulation,Data preparation,Data engineering,Feature scaling,One-hot encoding,Data imputation,Null value handling,Data exploration,Data processing,wizcraft,wiz-craft,WizCraft
Classifier: Programming Language :: Python :: 3
Classifier: Intended Audience :: Developers
Classifier: Operating System :: MacOS :: MacOS X
Classifier: Operating System :: Microsoft :: Windows
Classifier: Operating System :: Unix
License-File: LICENSE
Requires-Dist: numpy
Requires-Dist: pandas
Requires-Dist: scikit-learn
Requires-Dist: scipy
Requires-Dist: pandoc
